openpyxl_utilities/__init__.py
openpyxl_utilities-0.5.dist-info/METADATA
openpyxl_utilities-0.5.dist-info/RECORD
openpyxl_utilities-0.5.dist-info/WHEEL
openpyxl_utilities-0.5.dist-info/top_level.txt
