Metadata-Version: 2.1
Name: openpyxl_utilities
Version: 0.5
Summary: Library of functions with utilities for the popular xlsx Python module openpyxl
Home-page: https://github.com/SebastianMCarreira/openpyxl_utils
Author: Sebastian Matias Carreira
Author-email: sebastian.m.carreira@gmail.com
License: UNKNOWN
Platform: UNKNOWN
Classifier: Programming Language :: Python :: 3
Classifier: License :: OSI Approved :: MIT License
Classifier: Operating System :: OS Independent
